<?xml version="1.0" encoding="utf-8"?>
<!DOCTYPE hibernate-mapping PUBLIC "-//Hibernate/Hibernate Mapping DTD 3.0//EN"
"http://hibernate.sourceforge.net/hibernate-mapping-3.0.dtd">
<!-- 
    Mapping file autogenerated by MyEclipse Persistence Tools
-->
<hibernate-mapping>
    <class name="com.ews.bean.Econtrol" table="econtrol" catalog="ewsdb">
        <id name="coid" type="java.lang.Integer">
            <column name="coid" />
            <generator class="native" />
        </id>
        <many-to-one name="emodel" class="com.ews.bean.Emodel" fetch="select">
            <column name="comid" />
        </many-to-one>
        <many-to-one name="echannels" class="com.ews.bean.Echannels" fetch="select">
            <column name="cochid" />
        </many-to-one>
        <property name="cotitle" type="java.lang.String">
            <column name="cotitle" length="100" />
        </property>
        <property name="courl" type="java.lang.String">
            <column name="courl" />
        </property>
        <property name="coabout" type="java.lang.String">
            <column name="coabout" />
        </property>
        <property name="coname" type="java.lang.String">
            <column name="coname" length="100" />
        </property>
        <property name="cotype" type="java.lang.Integer">
            <column name="cotype" />
        </property>
        <property name="contenttype" type="java.lang.Integer">
            <column name="contenttype" />
        </property>
        <property name="config" type="java.lang.String">
            <column name="config" />
        </property>
    </class>
</hibernate-mapping>
